bitsets/__init__.py
bitsets/bases.py
bitsets/combos.py
bitsets/integers.py
bitsets/meta.py
bitsets/series.py
bitsets/transform.py
bitsets/visualize.py
bitsets-0.9.dist-info/licenses/LICENSE.txt
bitsets-0.9.dist-info/METADATA
bitsets-0.9.dist-info/WHEEL
bitsets-0.9.dist-info/top_level.txt
bitsets-0.9.dist-info/RECORD
