Metadata-Version: 2.4
Name: bitsets
Version: 0.9
Summary: Ordered subsets over a predefined domain
Author-email: Sebastian Bank <sebastian.bank@uni-leipzig.de>
License-Expression: MIT
Project-URL: Homepage, https://github.com/xflr6/bitsets
Project-URL: Documentation, https://bitsets.readthedocs.io
Project-URL: Changelog, https://bitsets.readthedocs.io/en/latest/changelog.html
Project-URL: Issue Tracker, https://github.com/xflr6/bitsets/issues
Project-URL: CI, https://github.com/xflr6/bitsets/actions
Project-URL: Coverage, https://codecov.io/gh/xflr6/bitsets
Keywords: ordered set,finite,immutable,bit string,array,map,field
Platform: any
Classifier: Development Status :: 4 - Beta
Classifier: Intended Audience :: Developers
Classifier: Operating System :: OS Independent
Classifier: Programming Language :: Python :: 3
Classifier: Programming Language :: Python :: 3.10
Classifier: Programming Language :: Python :: 3.11
Classifier: Programming Language :: Python :: 3.12
Classifier: Programming Language :: Python :: 3.13
Classifier: Programming Language :: Python :: 3.14
Requires-Python: >=3.10
License-File: LICENSE.txt
Provides-Extra: dev
Requires-Dist: build; extra == "dev"
Requires-Dist: wheel; extra == "dev"
Requires-Dist: twine; extra == "dev"
Requires-Dist: mypy; extra == "dev"
Requires-Dist: flake8; extra == "dev"
Requires-Dist: Flake8-pyproject; extra == "dev"
Requires-Dist: pep8-naming; extra == "dev"
Requires-Dist: tox>=3; extra == "dev"
Provides-Extra: test
Requires-Dist: pytest>=7; extra == "test"
Requires-Dist: pytest-cov; extra == "test"
Provides-Extra: docs
Requires-Dist: sphinx; extra == "docs"
Requires-Dist: sphinx-rtd-theme; extra == "docs"
Requires-Dist: sphinx-rtd-theme; extra == "docs"
Provides-Extra: visualization
Requires-Dist: graphviz~=0.7; extra == "visualization"
Dynamic: license-file
